est/__init__.py
est/__main__.py
est/settings.py
est/app/__init__.py
est/app/xas_viewer.py
est/app/utils/__init__.py
est/app/utils/url.py
est/core/__init__.py
est/core/monotonic.py
est/core/sections.py
est/core/split.py
est/core/units.py
est/core/io/__init__.py
est/core/io/information.py
est/core/io/read_xas.py
est/core/io/write_xas.py
est/core/io/_utils/__init__.py
est/core/io/_utils/ascii.py
est/core/io/_utils/load.py
est/core/io/_utils/parse.py
est/core/io/_utils/readers/__init__.py
est/core/io/_utils/readers/ascii_reader.py
est/core/io/_utils/readers/fabio_reader.py
est/core/io/_utils/readers/larch_reader.py
est/core/io/_utils/readers/silx_reader.py
est/core/io/_utils/readers/spec_reader.py
est/core/process/__init__.py
est/core/process/base.py
est/core/process/energyroi.py
est/core/process/handle_nan.py
est/core/process/ignoreprocess.py
est/core/process/io.py
est/core/process/noise.py
est/core/process/plotspectrumdata.py
est/core/process/progress.py
est/core/process/read.py
est/core/process/roi.py
est/core/process/split.py
est/core/process/write.py
est/core/process/larch/__init__.py
est/core/process/larch/autobk.py
est/core/process/larch/mback.py
est/core/process/larch/mback_norm.py
est/core/process/larch/pre_edge.py
est/core/process/larch/xftf.py
est/core/process/pymca/__init__.py
est/core/process/pymca/exafs.py
est/core/process/pymca/ft.py
est/core/process/pymca/k_weight.py
est/core/process/pymca/normalization.py
est/core/types/__init__.py
est/core/types/data.py
est/core/types/dimensions.py
est/core/types/sample.py
est/core/types/spectra.py
est/core/types/spectrum.py
est/core/types/xasobject.py
est/core/utils/__init__.py
est/core/utils/converter.py
est/core/utils/designpattern.py
est/core/utils/larchutils.py
est/gui/SpectrumPlot.py
est/gui/XasObjectViewer.py
est/gui/__init__.py
est/gui/energyroi.py
est/gui/icons.py
est/gui/noise.py
est/gui/qtapplicationmanager.py
est/gui/roiselector.py
est/gui/larch/__init__.py
est/gui/larch/autobk.py
est/gui/larch/mback.py
est-2.0.0.dist-info/licenses/LICENSE
est-2.0.0.dist-info/METADATA
est-2.0.0.dist-info/WHEEL
est-2.0.0.dist-info/entry_points.txt
est-2.0.0.dist-info/top_level.txt
est-2.0.0.dist-info/RECORD
