Metadata-Version: 2.4
Name: est
Version: 2.0.0
Summary: Spectroscopy workflows
Author-email: ESRF <dau-pydev@esrf.fr>
License: 
Project-URL: Homepage, https://gitlab.esrf.fr/workflow/ewoksapps/est/
Project-URL: Documentation, https://ewoksest.readthedocs.io/
Project-URL: Repository, https://gitlab.esrf.fr/workflow/ewoksapps/est/
Project-URL: Issues, https://gitlab.esrf.fr/workflow/ewoksapps/est/issues
Project-URL: Changelog, https://gitlab.esrf.fr/workflow/ewoksapps/est/-/blob/main/CHANGELOG.md
Keywords: orange3 add-on,ewoks
Classifier: Intended Audience :: Science/Research
Classifier: License :: OSI Approved :: MIT License
Classifier: Programming Language :: Python :: 3
Requires-Python: >=3.8
License-File: LICENSE
Requires-Dist: numpy
Requires-Dist: pydantic>=2
Requires-Dist: scipy
Requires-Dist: h5py>=3.1
Requires-Dist: silx>=0.15
Requires-Dist: Pint
Requires-Dist: ewokscore
Requires-Dist: ewoksorange>=3.1.0
Requires-Dist: importlib_resources; python_version < "3.9"
Provides-Extra: pymca
Requires-Dist: pymca>=5.8.1; extra == "pymca"
Provides-Extra: larch
Requires-Dist: xraylarch>=0.9.71; extra == "larch"
Provides-Extra: orange
Requires-Dist: ewoksorange[orange]>=3.1.0; extra == "orange"
Provides-Extra: full
Requires-Dist: est[pymca]; extra == "full"
Requires-Dist: est[larch]; extra == "full"
Requires-Dist: est[orange]; extra == "full"
Provides-Extra: test-no-larch-or-pymca
Requires-Dist: pytest>=7; extra == "test-no-larch-or-pymca"
Requires-Dist: testbook; extra == "test-no-larch-or-pymca"
Requires-Dist: ipykernel; extra == "test-no-larch-or-pymca"
Requires-Dist: pyqt5; extra == "test-no-larch-or-pymca"
Provides-Extra: test
Requires-Dist: ewoks; extra == "test"
Requires-Dist: est[full]; extra == "test"
Requires-Dist: est[test_no_larch_or_pymca]; extra == "test"
Provides-Extra: dev
Requires-Dist: est[test]; extra == "dev"
Requires-Dist: black>=25; extra == "dev"
Requires-Dist: flake8>=4; extra == "dev"
Requires-Dist: flake8_nb>=0.3.1; extra == "dev"
Requires-Dist: pillow>=10.0; extra == "dev"
Requires-Dist: isort; extra == "dev"
Provides-Extra: doc
Requires-Dist: est[test]; extra == "doc"
Requires-Dist: est[full]; extra == "doc"
Requires-Dist: sphinx>=4.5; extra == "doc"
Requires-Dist: sphinx-autodoc-typehints>=1.16; extra == "doc"
Requires-Dist: ipykernel; extra == "doc"
Requires-Dist: nbsphinx; extra == "doc"
Requires-Dist: nbsphinx_link; extra == "doc"
Requires-Dist: docutils<0.21; extra == "doc"
Requires-Dist: pydata_sphinx_theme; extra == "doc"
Requires-Dist: sphinx-copybutton; extra == "doc"
Dynamic: license-file
